[{"created":1683532501722,"labels":[{"status":"ACTIVE","name":"Sport","id":1},{"status":"DELETED","name":"Sex","id":5}],"status":"DELETED","writer":{"firstName":"Ray","lastName":"Bradberry","status":"ACTIVE","id":1},"id":1},{"created":1683532523840,"labels":[{"status":"DELETED","name":"Rest","id":3}],"status":"ACTIVE","writer":{"firstName":"Jack","lastName":"London","status":"DELETED","id":2},"id":2},{"updated":1683532543317,"labels":[{"status":"DELETED","name":"Sex","id":5}],"status":"DELETED","writer":{"firstName":"Ray","lastName":"Bradberry","status":"ACTIVE","id":1},"id":1},{"updated":1683532562728,"labels":[{"status":"ACTIVE","name":"Life","id":2}],"status":"UNDER_REVIEW","writer":{"firstName":"Jack","lastName":"London","status":"DELETED","id":2},"id":1}]